Topsis/__init__.py
Topsis/__main__.py
Topsis_Rohan_102103108-1.1.2.dist-info/METADATA
Topsis_Rohan_102103108-1.1.2.dist-info/WHEEL
Topsis_Rohan_102103108-1.1.2.dist-info/entry_points.txt
Topsis_Rohan_102103108-1.1.2.dist-info/top_level.txt
Topsis_Rohan_102103108-1.1.2.dist-info/RECORD
