Metadata-Version: 2.1
Name: Topsis-Rohan-102103108
Version: 1.1.2
Summary: Topsis-Rohan-102103108
Home-page: https://github.com/Rohan1405/Topsis-Rohan-102103108
Author: Rohan Gulati
Author-email: gulatirohan2003@gmail.com
License: MIT
Classifier: License :: OSI Approved :: MIT License
Classifier: Programming Language :: Python :: 3.6
Classifier: Programming Language :: Python :: 3.7
Classifier: Programming Language :: Python :: 3.8
